c2client/__init__.py
c2client/c2rc_convert.py
c2client/clients.py
c2client/errors.py
c2client/utils.py
c2client-0.25.dist-info/METADATA
c2client-0.25.dist-info/WHEEL
c2client-0.25.dist-info/entry_points.txt
c2client-0.25.dist-info/top_level.txt
c2client-0.25.dist-info/RECORD
