Metadata-Version: 2.1
Name: c2client
Version: 0.25
Summary: CROC Cloud Platform - API Client
Home-page: https://github.com/c2devel/c2-client
Author: CROC Cloud Team
Author-email: devel@croc.ru
Maintainer: Andrey Kulaev
Maintainer-email: adkulaev@gmail.com
License: GPL3
Platform: UNKNOWN
Classifier: Development Status :: 5 - Production/Stable
Classifier: Environment :: Console
Classifier: Intended Audience :: Developers
Classifier: Intended Audience :: System Administrators
Classifier: Operating System :: OS Independent
Classifier: Programming Language :: Python :: 3
Classifier: Programming Language :: Python :: 3.6
Classifier: Programming Language :: Python :: 3.7
Classifier: Programming Language :: Python :: 3.8
Classifier: Programming Language :: Python :: 3.9
Classifier: Programming Language :: Python :: 3.10
Classifier: Programming Language :: Python :: 3.11
Classifier: Programming Language :: Python :: 3.12
Classifier: Programming Language :: Python :: 3.13
Requires-Dist: boto3
Requires-Dist: botocore
Requires-Dist: inflection==0.3.1
